nonesafe.py
nonesafe-0.1.7.dist-info/LICENSE
nonesafe-0.1.7.dist-info/METADATA
nonesafe-0.1.7.dist-info/WHEEL
nonesafe-0.1.7.dist-info/top_level.txt
nonesafe-0.1.7.dist-info/RECORD
