Metadata-Version: 2.2
Name: nonesafe
Version: 0.1.7
Summary: ``nonesafe``: safe to read, write, and read/modify/write ``dicts`` from external data
Home-page: https://github.com/hlovatt/nonesafe
Author: Howard C Lovatt.
Author-email: howard.lovatt@gmail.com
License: MIT License
Platform: any
Classifier: Intended Audience :: Developers
Classifier: Programming Language :: Python :: 3
Classifier: License :: OSI Approved :: MIT License
Classifier: Operating System :: OS Independent
Requires-Python: >=3.12
License-File: LICENSE
Dynamic: author
Dynamic: author-email
Dynamic: classifier
Dynamic: description
Dynamic: description-content-type
Dynamic: home-page
Dynamic: license
Dynamic: platform
Dynamic: requires-python
Dynamic: summary
